{
  "easy": [
    {"word": "happy", "synonyms": ["joyful", "cheerful", "content", "delighted", "pleased"]},
    {"word": "big", "synonyms": ["large", "huge", "gigantic", "massive", "enormous"]},
    {"word": "fast", "synonyms": ["quick", "speedy", "swift", "rapid", "hasty"]},
    {"word": "cold", "synonyms": ["chilly", "freezing", "icy", "cool", "frosty"]},
    {"word": "small", "synonyms": ["tiny", "miniature", "petite", "little", "minute"]},
    {"word": "smart", "synonyms": ["intelligent", "clever", "bright", "wise", "brilliant"]},
    {"word": "strong", "synonyms": ["powerful", "sturdy", "tough", "solid", "resilient"]},
    {"word": "kind", "synonyms": ["nice", "caring", "compassionate", "thoughtful", "gentle"]},
    {"word": "funny", "synonyms": ["humorous", "hilarious", "amusing", "entertaining", "witty"]},
    {"word": "tired", "synonyms": ["exhausted", "sleepy", "fatigued", "weary", "worn-out"]},
    {"word": "soft", "synonyms": ["gentle", "smooth", "delicate", "tender", "fluffy"]},
    {"word": "angry", "synonyms": ["mad", "furious", "upset", "irritated", "annoyed"]},
    {"word": "beautiful", "synonyms": ["pretty", "lovely", "gorgeous", "attractive", "stunning"]},
    {"word": "brave", "synonyms": ["courageous", "fearless", "bold", "valiant", "heroic"]},
    {"word": "easy", "synonyms": ["simple", "effortless", "straightforward", "clear", "uncomplicated"]},
    {"word": "old", "synonyms": ["ancient", "elderly", "aged", "vintage", "antique"]},
    {"word": "new", "synonyms": ["fresh", "modern", "recent", "current", "updated"]},
    {"word": "dark", "synonyms": ["dim", "shadowy", "gloomy", "murky", "dusky"]},
    {"word": "happy", "synonyms": ["cheerful", "glad", "joyous", "jovial", "merry"]},
    {"word": "sad", "synonyms": ["unhappy", "miserable", "downcast", "sorrowful", "depressed"]},
    {"word": "friendly", "synonyms": ["kind", "nice", "pleasant", "warm", "helpful"]},
    {"word": "loud", "synonyms": ["noisy", "boisterous", "deafening", "thunderous", "blaring"]},
    {"word": "quiet", "synonyms": ["silent", "hushed", "muted", "soft", "calm"]},
    {"word": "lazy", "synonyms": ["inactive", "idle", "sluggish", "lethargic", "slow"]},
    {"word": "hungry", "synonyms": ["starving", "famished", "ravenous", "empty", "hollow"]},
    {"word": "clean", "synonyms": ["tidy", "neat", "spotless", "pristine", "sanitary"]},
    {"word": "dirty", "synonyms": ["filthy", "messy", "muddy", "grimy", "unclean"]},
    {"word": "hot", "synonyms": ["warm", "scorching", "blazing", "boiling", "sizzling"]},
    {"word": "strong", "synonyms": ["powerful", "sturdy", "tough", "solid", "hardy"]},
    {"word": "weak", "synonyms": ["frail", "feeble", "delicate", "fragile", "wobbly"]},
    {"word": "fast", "synonyms": ["quick", "speedy", "swift", "rapid", "hasty"]},
    {"word": "slow", "synonyms": ["lethargic", "sluggish", "unhurried", "gradual", "delayed"]},
    {"word": "shy", "synonyms": ["timid", "bashful", "nervous", "introverted", "reserved"]},
    {"word": "brave", "synonyms": ["bold", "fearless", "courageous", "daring", "heroic"]},
    {"word": "sleepy", "synonyms": ["tired", "drowsy", "weary", "exhausted", "fatigued"]},
    {"word": "bright", "synonyms": ["radiant", "luminous", "shiny", "glowing", "vivid"]},
    {"word": "wet", "synonyms": ["damp", "soaked", "dripping", "soggy", "humid"]},
    {"word": "happy", "synonyms": ["cheerful", "joyful", "content", "gleeful", "jolly"]},
    {"word": "sad", "synonyms": ["unhappy", "downcast", "miserable", "gloomy", "sorrowful"]},
    {"word": "angry", "synonyms": ["furious", "mad", "annoyed", "irritated", "enraged"]},
    {"word": "friendly", "synonyms": ["kind", "nice", "pleasant", "warm", "helpful"]},
    {"word": "loud", "synonyms": ["noisy", "boisterous", "deafening", "thunderous", "blaring"]},
    {"word": "quiet", "synonyms": ["silent", "hushed", "muted", "soft", "calm"]},
    {"word": "lazy", "synonyms": ["inactive", "idle", "sluggish", "lethargic", "slow"]},
    {"word": "hungry", "synonyms": ["starving", "famished", "ravenous", "empty", "hollow"]},
    {"word": "clean", "synonyms": ["tidy", "neat", "spotless", "pristine", "sanitary"]},
    {"word": "dirty", "synonyms": ["filthy", "messy", "muddy", "grimy", "unclean"]},
    {"word": "hot", "synonyms": ["warm", "scorching", "blazing", "boiling", "sizzling"]},
    {"word": "strong", "synonyms": ["powerful", "sturdy", "tough", "solid", "hardy"]},
    {"word": "weak", "synonyms": ["frail", "feeble", "delicate", "fragile", "wobbly"]},
    {"word": "fast", "synonyms": ["quick", "speedy", "swift", "rapid", "hasty"]},
    {"word": "slow", "synonyms": ["lethargic", "sluggish", "unhurried", "gradual", "delayed"]},
    {"word": "shy", "synonyms": ["timid", "bashful", "nervous", "introverted", "reserved"]},
    {"word": "brave", "synonyms": ["bold", "fearless", "courageous", "daring", "heroic"]},
    {"word": "sleepy", "synonyms": ["tired", "drowsy", "weary", "exhausted", "fatigued"]},
    {"word": "bright", "synonyms": ["radiant", "luminous", "shiny", "glowing", "vivid"]},
    {"word": "wet", "synonyms": ["damp", "soaked", "dripping", "soggy", "humid"]},
    {"word": "happy", "synonyms": ["cheerful", "joyful", "content", "gleeful", "jolly"]},
    {"word": "sad", "synonyms": ["unhappy", "downcast", "miserable", "gloomy", "sorrowful"]},
    {"word": "angry", "synonyms": ["furious", "mad", "annoyed", "irritated", "enraged"]},
    {"word": "talk", "synonyms": ["speak", "chat", "discuss", "converse", "communicate"]},
    {"word": "run", "synonyms": ["jog", "sprint", "dash", "race", "hurry"]},
    {"word": "sit", "synonyms": ["rest", "perch", "settle", "plop", "relax"]},
    {"word": "big", "synonyms": ["huge", "giant", "large", "massive", "colossal"]},
    {"word": "tiny", "synonyms": ["small", "mini", "little", "petite", "diminutive"]},
    {"word": "nice", "synonyms": ["kind", "polite", "friendly", "sweet", "thoughtful"]},
    {"word": "mean", "synonyms": ["rude", "cruel", "harsh", "unkind", "nasty"]},
    {"word": "shine", "synonyms": ["glow", "gleam", "sparkle", "radiate", "beam"]},
    {"word": "loud", "synonyms": ["noisy", "booming", "deafening", "thunderous", "blaring"]},
    {"word": "quiet", "synonyms": ["silent", "hushed", "muted", "soft", "whispered"]},
    {"word": "jump", "synonyms": ["leap", "hop", "bounce", "vault", "spring"]},
    {"word": "sad", "synonyms": ["unhappy", "tearful", "blue", "miserable", "downcast"]},
    {"word": "smile", "synonyms": ["grin", "beam", "smirk", "laugh", "chuckle"]},
    {"word": "strong", "synonyms": ["powerful", "mighty", "tough", "sturdy", "hardy"]},
    {"word": "weak", "synonyms": ["frail", "feeble", "delicate", "flimsy", "brittle"]},
    {"word": "love", "synonyms": ["adore", "cherish", "appreciate", "treasure", "care for"]},
    {"word": "hate", "synonyms": ["dislike", "detest", "despise", "abhor", "loathe"]},
    {"word": "fun", "synonyms": ["exciting", "enjoyable", "thrilling", "entertaining", "amusing"]},
    {"word": "boring", "synonyms": ["dull", "uninteresting", "tedious", "bland", "monotonous"]},
    {"word": "hard", "synonyms": ["difficult", "challenging", "tough", "tricky", "complicated"]},
    {"word": "jump", "synonyms": ["leap", "hop", "bounce", "vault", "spring"]},
    {"word": "walk", "synonyms": ["stroll", "stride", "saunter", "march", "amble"]},
    {"word": "talk", "synonyms": ["chat", "speak", "converse", "discuss", "communicate"]},
    {"word": "laugh", "synonyms": ["giggle", "chuckle", "snicker", "cackle", "guffaw"]},
    {"word": "cry", "synonyms": ["weep", "sob", "bawl", "tear up", "whimper"]},
    {"word": "hot", "synonyms": ["warm", "scorching", "boiling", "sizzling", "blazing"]},
    {"word": "cold", "synonyms": ["chilly", "freezing", "frosty", "icy", "nippy"]},
    {"word": "soft", "synonyms": ["fluffy", "cushiony", "smooth", "tender", "silky"]},
    {"word": "hard", "synonyms": ["firm", "rigid", "sturdy", "solid", "tough"]},
    {"word": "light", "synonyms": ["bright", "radiant", "luminous", "glowing", "shiny"]},
    {"word": "dark", "synonyms": ["dim", "shadowy", "murky", "gloomy", "dull"]},
    {"word": "big", "synonyms": ["huge", "large", "massive", "gigantic", "colossal"]},
    {"word": "small", "synonyms": ["tiny", "little", "miniature", "petite", "compact"]},
    {"word": "quick", "synonyms": ["fast", "speedy", "swift", "rapid", "brisk"]},
    {"word": "slow", "synonyms": ["lethargic", "gradual", "unhurried", "deliberate", "snail-paced"]},
    {"word": "easy", "synonyms": ["simple", "effortless", "straightforward", "basic", "clear"]},
    {"word": "difficult", "synonyms": ["challenging", "tough", "complicated", "tricky", "hard"]},
    {"word": "clean", "synonyms": ["tidy", "neat", "spotless", "pristine", "sanitary"]},
    {"word": "dirty", "synonyms": ["messy", "muddy", "grimy", "filthy", "unclean"]},
    {"word": "kind", "synonyms": ["nice", "caring", "polite", "thoughtful", "gentle"]}
  ],
  "medium": [
    {"word": "diligent", "synonyms": ["hardworking", "industrious", "persevering", "thorough", "attentive"]},
    {"word": "cautious", "synonyms": ["careful", "wary", "watchful", "prudent", "alert"]},
    {"word": "generous", "synonyms": ["charitable", "kind", "benevolent", "selfless", "giving"]},
    {"word": "mysterious", "synonyms": ["enigmatic", "puzzling", "secretive", "cryptic", "unexplained"]},
    {"word": "vibrant", "synonyms": ["colorful", "lively", "energetic", "radiant", "spirited"]},
    {"word": "timid", "synonyms": ["shy", "nervous", "hesitant", "fearful", "meek"]},
    {"word": "fragile", "synonyms": ["delicate", "brittle", "weak", "breakable", "frail"]},
    {"word": "precise", "synonyms": ["exact", "accurate", "correct", "definite", "specific"]},
    {"word": "remote", "synonyms": ["distant", "isolated", "faraway", "secluded", "hidden"]},
    {"word": "dense", "synonyms": ["thick", "compact", "solid", "impenetrable", "opaque"]},
    {"word": "perplexed", "synonyms": ["confused", "baffled", "puzzled", "bewildered", "stumped"]},
    {"word": "reluctant", "synonyms": ["hesitant", "unwilling", "resistant", "uncertain", "unsure"]},
    {"word": "elaborate", "synonyms": ["detailed", "intricate", "complex", "thorough", "decorative"]},
    {"word": "nourish", "synonyms": ["feed", "sustain", "support", "maintain", "strengthen"]},
    {"word": "affectionate", "synonyms": ["loving", "caring", "warm", "tender", "devoted"]},
    {"word": "composed", "synonyms": ["calm", "collected", "serene", "poised", "level-headed"]},
    {"word": "ominous", "synonyms": ["threatening", "foreboding", "menacing", "dark", "sinister"]},
    {"word": "brisk", "synonyms": ["quick", "energetic", "lively", "rapid", "refreshing"]},
    {"word": "lofty", "synonyms": ["elevated", "high", "grand", "majestic", "towering"]},
    {"word": "rigid", "synonyms": ["stiff", "firm", "unyielding", "strict", "inflexible"]},
    {"word": "sturdy", "synonyms": ["strong", "robust", "durable", "tough", "solid"]},
    {"word": "vague", "synonyms": ["unclear", "indistinct", "fuzzy", "ambiguous", "blurred"]},
    {"word": "decent", "synonyms": ["respectable", "honest", "proper", "modest", "fair"]},
    {"word": "tedious", "synonyms": ["boring", "dull", "monotonous", "repetitive", "tiresome"]},
    {"word": "vicious", "synonyms": ["cruel", "ferocious", "brutal", "savage", "ruthless"]},
    {"word": "cozy", "synonyms": ["comfortable", "warm", "snug", "homely", "pleasant"]},
    {"word": "eager", "synonyms": ["enthusiastic", "excited", "keen", "willing", "anxious"]},
    {"word": "sincere", "synonyms": ["honest", "genuine", "truthful", "authentic", "heartfelt"]},
    {"word": "peculiar", "synonyms": ["odd", "strange", "unusual", "bizarre", "quirky"]},
    {"word": "reckless", "synonyms": ["careless", "rash", "impulsive", "hasty", "irresponsible"]},
    {"word": "modest", "synonyms": ["humble", "reserved", "meek", "shy", "moderate"]},
    {"word": "delicate", "synonyms": ["fragile", "sensitive", "dainty", "soft", "elegant"]},
    {"word": "dreadful", "synonyms": ["terrible", "horrible", "frightening", "awful", "appalling"]},
    {"word": "stubborn", "synonyms": ["headstrong", "unyielding", "persistent", "obstinate", "tenacious"]},
    {"word": "vivid", "synonyms": ["bright", "colorful", "intense", "radiant", "striking"]},
    {"word": "stern", "synonyms": ["strict", "harsh", "severe", "firm", "rigid"]},
    {"word": "nimble", "synonyms": ["agile", "quick", "dexterous", "lively", "graceful"]},
    {"word": "trivial", "synonyms": ["insignificant", "minor", "petty", "unimportant", "negligible"]},
    {"word": "graceful", "synonyms": ["elegant", "poised", "refined", "smooth", "flowing"]},
    {"word": "sly", "synonyms": ["cunning", "tricky", "sneaky", "devious", "crafty"]},
    {"word": "sturdy", "synonyms": ["strong", "robust", "durable", "tough", "solid"]},
    {"word": "vague", "synonyms": ["unclear", "indistinct", "fuzzy", "ambiguous", "blurred"]},
    {"word": "decent", "synonyms": ["respectable", "honest", "proper", "modest", "fair"]},
    {"word": "tedious", "synonyms": ["boring", "dull", "monotonous", "repetitive", "tiresome"]},
    {"word": "vicious", "synonyms": ["cruel", "ferocious", "brutal", "savage", "ruthless"]},
    {"word": "cozy", "synonyms": ["comfortable", "warm", "snug", "homely", "pleasant"]},
    {"word": "eager", "synonyms": ["enthusiastic", "excited", "keen", "willing", "anxious"]},
    {"word": "sincere", "synonyms": ["honest", "genuine", "truthful", "authentic", "heartfelt"]},
    {"word": "peculiar", "synonyms": ["odd", "strange", "unusual", "bizarre", "quirky"]},
    {"word": "reckless", "synonyms": ["careless", "rash", "impulsive", "hasty", "irresponsible"]},
    {"word": "modest", "synonyms": ["humble", "reserved", "meek", "shy", "moderate"]},
    {"word": "delicate", "synonyms": ["fragile", "sensitive", "dainty", "soft", "elegant"]},
    {"word": "dreadful", "synonyms": ["terrible", "horrible", "frightening", "awful", "appalling"]},
    {"word": "stubborn", "synonyms": ["headstrong", "unyielding", "persistent", "obstinate", "tenacious"]},
    {"word": "vivid", "synonyms": ["bright", "colorful", "intense", "radiant", "striking"]},
    {"word": "stern", "synonyms": ["strict", "harsh", "severe", "firm", "rigid"]},
    {"word": "nimble", "synonyms": ["agile", "quick", "dexterous", "lively", "graceful"]},
    {"word": "trivial", "synonyms": ["insignificant", "minor", "petty", "unimportant", "negligible"]},
    {"word": "graceful", "synonyms": ["elegant", "poised", "refined", "smooth", "flowing"]},
    {"word": "sly", "synonyms": ["cunning", "tricky", "sneaky", "devious", "crafty"]},
    {"word": "mature", "synonyms": ["grown", "adult", "developed", "responsible", "wise"]},
    {"word": "youthful", "synonyms": ["young", "childlike", "fresh", "lively", "energetic"]},
    {"word": "confident", "synonyms": ["assured", "bold", "certain", "self-reliant", "fearless"]},
    {"word": "timid", "synonyms": ["shy", "nervous", "hesitant", "fearful", "meek"]},
    {"word": "fortunate", "synonyms": ["lucky", "blessed", "prosperous", "successful", "favored"]},
    {"word": "unlucky", "synonyms": ["unfortunate", "doomed", "cursed", "misfortunate", "ill-fated"]},
    {"word": "charming", "synonyms": ["attractive", "charismatic", "appealing", "delightful", "engaging"]},
    {"word": "demanding", "synonyms": ["challenging", "difficult", "strict", "exacting", "tiring"]},
    {"word": "polished", "synonyms": ["refined", "smooth", "sophisticated", "elegant", "gleaming"]},
    {"word": "messy", "synonyms": ["untidy", "cluttered", "disorganized", "chaotic", "jumbled"]},
    {"word": "persistent", "synonyms": ["determined", "unwavering", "resilient", "stubborn", "tenacious"]},
    {"word": "fickle", "synonyms": ["unpredictable", "changeable", "whimsical", "unreliable", "capricious"]},
    {"word": "cruel", "synonyms": ["mean", "harsh", "brutal", "vicious", "merciless"]},
    {"word": "graceful", "synonyms": ["elegant", "poised", "fluid", "refined", "lithe"]},
    {"word": "stiff", "synonyms": ["rigid", "unyielding", "tense", "inflexible", "hard"]},
    {"word": "elated", "synonyms": ["joyful", "overjoyed", "ecstatic", "exuberant", "jubilant"]},
    {"word": "gloomy", "synonyms": ["dark", "dreary", "melancholy", "dismal", "somber"]},
    {"word": "reliable", "synonyms": ["trustworthy", "dependable", "consistent", "faithful", "steadfast"]},
    {"word": "fragile", "synonyms": ["delicate", "brittle", "weak", "breakable", "frail"]},
    {"word": "hefty", "synonyms": ["heavy", "massive", "bulky", "large", "solid"]},
    {"word": "mysterious", "synonyms": ["enigmatic", "secretive", "cryptic", "puzzling", "obscure"]},
    {"word": "brilliant", "synonyms": ["intelligent", "genius", "bright", "remarkable", "dazzling"]},
    {"word": "stern", "synonyms": ["strict", "harsh", "severe", "firm", "unyielding"]},
    {"word": "humble", "synonyms": ["modest", "meek", "reserved", "self-effacing", "unassuming"]},
    {"word": "reckless", "synonyms": ["careless", "rash", "impulsive", "hasty", "irresponsible"]},
    {"word": "cautious", "synonyms": ["wary", "careful", "prudent", "vigilant", "watchful"]},
    {"word": "cheerful", "synonyms": ["joyful", "happy", "bright", "lively", "merry"]},
    {"word": "desperate", "synonyms": ["hopeless", "frantic", "urgent", "critical", "dire"]},
    {"word": "suspicious", "synonyms": ["doubtful", "questioning", "skeptical", "uncertain", "mistrustful"]},
    {"word": "inspired", "synonyms": ["motivated", "encouraged", "driven", "energized", "uplifted"]},
    {"word": "fierce", "synonyms": ["aggressive", "ferocious", "intense", "powerful", "strong"]},
    {"word": "loyal", "synonyms": ["faithful", "devoted", "trustworthy", "reliable", "steadfast"]},
    {"word": "melancholy", "synonyms": ["sad", "sorrowful", "gloomy", "downcast", "mournful"]},
    {"word": "curious", "synonyms": ["inquisitive", "interested", "eager", "questioning", "nosy"]},
    {"word": "gentle", "synonyms": ["kind", "soft", "tender", "delicate", "mild"]},
    {"word": "anxious", "synonyms": ["nervous", "worried", "apprehensive", "uneasy", "fearful"]},
    {"word": "bold", "synonyms": ["brave", "fearless", "daring", "courageous", "valiant"]},
    {"word": "vivid", "synonyms": ["bright", "colorful", "intense", "lively", "radiant"]},
    {"word": "delicate", "synonyms": ["fragile", "dainty", "fine", "elegant", "subtle"]},
    {"word": "persistent", "synonyms": ["determined", "unwavering", "relentless", "tenacious", "resilient"]}
  ],
  "hard": [
    {"word": "ephemeral", "synonyms": ["fleeting", "short-lived", "transitory", "momentary", "brief"]},
    {"word": "esoteric", "synonyms": ["obscure", "mysterious", "complex", "specialized", "enigmatic"]},
    {"word": "fastidious", "synonyms": ["meticulous", "precise", "perfectionist", "scrupulous", "thorough"]},
    {"word": "altruistic", "synonyms": ["selfless", "charitable", "philanthropic", "benevolent", "kind"]},
    {"word": "gregarious", "synonyms": ["sociable", "outgoing", "friendly", "companionable", "extroverted"]},
    {"word": "magnanimous", "synonyms": ["generous", "noble", "charitable", "selfless", "forgiving"]},
    {"word": "serendipitous", "synonyms": ["fortunate", "unexpected", "lucky", "coincidental", "unforeseen"]},
    {"word": "taciturn", "synonyms": ["reserved", "silent", "quiet", "reticent", "uncommunicative"]},
    {"word": "ubiquitous", "synonyms": ["omnipresent", "everywhere", "pervasive", "universal", "widespread"]},
    {"word": "circumspect", "synonyms": ["cautious", "wary", "prudent", "careful", "thoughtful"]},
    {"word": "intransigent", "synonyms": ["stubborn", "uncompromising", "unyielding", "rigid", "inflexible"]},
    {"word": "pernicious", "synonyms": ["harmful", "destructive", "damaging", "toxic", "malicious"]},
    {"word": "sagacious", "synonyms": ["wise", "insightful", "intelligent", "shrewd", "perceptive"]},
    {"word": "resplendent", "synonyms": ["brilliant", "radiant", "dazzling", "gleaming", "magnificent"]},
    {"word": "quotidian", "synonyms": ["daily", "ordinary", "routine", "mundane", "commonplace"]},
    {"word": "obfuscate", "synonyms": ["confuse", "complicate", "bewilder", "perplex", "cloud"]},
    {"word": "lugubrious", "synonyms": ["mournful", "gloomy", "melancholy", "somber", "depressing"]},
    {"word": "acquiesce", "synonyms": ["comply", "agree", "yield", "accept", "consent"]},
    {"word": "vindicate", "synonyms": ["justify", "clear", "absolve", "defend", "exonerate"]},
    {"word": "abstruse", "synonyms": ["obscure", "complicated", "esoteric", "perplexing", "enigmatic"]},
    {"word": "capricious", "synonyms": ["unpredictable", "whimsical", "impulsive", "fickle", "erratic"]},
    {"word": "sublime", "synonyms": ["majestic", "noble", "transcendent", "exalted", "glorious"]},
    {"word": "peremptory", "synonyms": ["authoritative", "absolute", "commanding", "decisive", "firm"]},
    {"word": "lugubrious", "synonyms": ["mournful", "gloomy", "melancholy", "somber", "woeful"]},
    {"word": "recalcitrant", "synonyms": ["defiant", "stubborn", "rebellious", "unruly", "resistant"]},
    {"word": "prodigious", "synonyms": ["enormous", "vast", "tremendous", "immense", "colossal"]},
    {"word": "torrid", "synonyms": ["scorching", "blazing", "boiling", "sizzling", "sweltering"]},
    {"word": "chicanery", "synonyms": ["deception", "trickery", "fraud", "duplicity", "dishonesty"]},
    {"word": "effulgent", "synonyms": ["radiant", "shining", "brilliant", "luminous", "glowing"]},
    {"word": "perspicacious", "synonyms": ["insightful", "perceptive", "shrewd", "astute", "keen"]},
    {"word": "unctuous", "synonyms": ["oily", "insincere", "smarmy", "obsequious", "ingratiating"]},
    {"word": "sycophant", "synonyms": ["flatterer", "bootlicker", "toady", "brown-noser", "kiss-up"]},
    {"word": "tenebrous", "synonyms": ["dark", "gloomy", "obscure", "murky", "shadowy"]},
    {"word": "obstreperous", "synonyms": ["rowdy", "boisterous", "unruly", "noisy", "disruptive"]},
    {"word": "equanimity", "synonyms": ["calmness", "composure", "serenity", "poise", "tranquility"]},
    {"word": "pulchritudinous", "synonyms": ["beautiful", "lovely", "gorgeous", "stunning", "radiant"]},
    {"word": "exigent", "synonyms": ["urgent", "pressing", "critical", "imperative", "demanding"]},
    {"word": "ineluctable", "synonyms": ["inevitable", "unavoidable", "inescapable", "certain", "fated"]},
    {"word": "abstruse", "synonyms": ["obscure", "complicated", "esoteric", "perplexing", "enigmatic"]},
    {"word": "capricious", "synonyms": ["unpredictable", "whimsical", "impulsive", "fickle", "erratic"]},
    {"word": "sublime", "synonyms": ["majestic", "noble", "transcendent", "exalted", "glorious"]},
    {"word": "peremptory", "synonyms": ["authoritative", "absolute", "commanding", "decisive", "firm"]},
    {"word": "lugubrious", "synonyms": ["mournful", "gloomy", "melancholy", "somber", "woeful"]},
    {"word": "recalcitrant", "synonyms": ["defiant", "stubborn", "rebellious", "unruly", "resistant"]},
    {"word": "prodigious", "synonyms": ["enormous", "vast", "tremendous", "immense", "colossal"]},
    {"word": "torrid", "synonyms": ["scorching", "blazing", "boiling", "sizzling", "sweltering"]},
    {"word": "chicanery", "synonyms": ["deception", "trickery", "fraud", "duplicity", "dishonesty"]},
    {"word": "effulgent", "synonyms": ["radiant", "shining", "brilliant", "luminous", "glowing"]},
    {"word": "perspicacious", "synonyms": ["insightful", "perceptive", "shrewd", "astute", "keen"]},
    {"word": "unctuous", "synonyms": ["oily", "insincere", "smarmy", "obsequious", "ingratiating"]},
    {"word": "sycophant", "synonyms": ["flatterer", "bootlicker", "toady", "brown-noser", "kiss-up"]},
    {"word": "tenebrous", "synonyms": ["dark", "gloomy", "obscure", "murky", "shadowy"]},
    {"word": "obstreperous", "synonyms": ["rowdy", "boisterous", "unruly", "noisy", "disruptive"]},
    {"word": "equanimity", "synonyms": ["calmness", "composure", "serenity", "poise", "tranquility"]},
    {"word": "pulchritudinous", "synonyms": ["beautiful", "lovely", "gorgeous", "stunning", "radiant"]},
    {"word": "exigent", "synonyms": ["urgent", "pressing", "critical", "imperative", "demanding"]},
    {"word": "ineluctable", "synonyms": ["inevitable", "unavoidable", "inescapable", "certain", "fated"]},
    {"word": "quixotic", "synonyms": ["idealistic", "unrealistic", "romantic", "impractical", "visionary"]},
    {"word": "surreptitious", "synonyms": ["secretive", "sly", "stealthy", "furtive", "covert"]},
    {"word": "lugubrious", "synonyms": ["mournful", "gloomy", "melancholy", "somber", "woeful"]},
    {"word": "ephemeral", "synonyms": ["short-lived", "fleeting", "transitory", "momentary", "brief"]},
    {"word": "obsequious", "synonyms": ["servile", "fawning", "submissive", "deferential", "sycophantic"]},
    {"word": "ineluctable", "synonyms": ["inevitable", "unavoidable", "inescapable", "certain", "fated"]},
    {"word": "tenebrous", "synonyms": ["dark", "shadowy", "gloomy", "murky", "obscure"]},
    {"word": "punctilious", "synonyms": ["meticulous", "precise", "scrupulous", "exact", "fastidious"]},
    {"word": "insidious", "synonyms": ["deceptive", "dangerous", "treacherous", "sly", "cunning"]},
    {"word": "prodigious", "synonyms": ["massive", "enormous", "tremendous", "monumental", "colossal"]},
    {"word": "grandiloquent", "synonyms": ["pompous", "bombastic", "pretentious", "lofty", "overblown"]},
    {"word": "laconic", "synonyms": ["concise", "terse", "brief", "succinct", "pithy"]},
    {"word": "deleterious", "synonyms": ["harmful", "damaging", "detrimental", "toxic", "pernicious"]},
    {"word": "obstreperous", "synonyms": ["noisy", "rowdy", "unruly", "disruptive", "boisterous"]},
    {"word": "sagacious", "synonyms": ["wise", "intelligent", "perceptive", "astute", "insightful"]},
    {"word": "ebullient", "synonyms": ["enthusiastic", "exuberant", "lively", "buoyant", "cheerful"]},
    {"word": "recalcitrant", "synonyms": ["stubborn", "uncooperative", "resistant", "defiant", "rebellious"]},
    {"word": "magnanimous", "synonyms": ["generous", "charitable", "benevolent", "selfless", "forgiving"]},
    {"word": "exigent", "synonyms": ["urgent", "pressing", "critical", "imperative", "demanding"]},
    {"word": "abstruse", "synonyms": ["obscure", "complex", "enigmatic", "difficult", "perplexing"]},
    {"word": "ephemeral", "synonyms": ["fleeting", "short-lived", "transitory", "momentary", "brief"]},
    {"word": "insidious", "synonyms": ["sly", "deceptive", "dangerous", "treacherous", "cunning"]},
    {"word": "ubiquitous", "synonyms": ["omnipresent", "pervasive", "everywhere", "widespread", "universal"]},
    {"word": "fastidious", "synonyms": ["meticulous", "precise", "demanding", "scrupulous", "perfectionist"]},
    {"word": "vociferous", "synonyms": ["loud", "noisy", "boisterous", "clamorous", "strident"]},
    {"word": "quixotic", "synonyms": ["idealistic", "romantic", "impractical", "unrealistic", "visionary"]},
    {"word": "pulchritudinous", "synonyms": ["beautiful", "gorgeous", "stunning", "radiant", "exquisite"]},
    {"word": "pernicious", "synonyms": ["harmful", "damaging", "toxic", "destructive", "malignant"]},
    {"word": "sagacious", "synonyms": ["wise", "insightful", "intelligent", "astute", "perceptive"]},
    {"word": "tenebrous", "synonyms": ["dark", "gloomy", "shadowy", "murky", "obscure"]},
    {"word": "abstruse", "synonyms": ["obscure", "complicated", "esoteric", "perplexing", "enigmatic"]},
    {"word": "laconic", "synonyms": ["concise", "terse", "brief", "succinct", "pithy"]},
    {"word": "obstreperous", "synonyms": ["rowdy", "boisterous", "unruly", "noisy", "disruptive"]},
    {"word": "chicanery", "synonyms": ["deception", "trickery", "fraud", "duplicity", "dishonesty"]},
    {"word": "exigent", "synonyms": ["urgent", "pressing", "critical", "imperative", "demanding"]},
    {"word": "recalcitrant", "synonyms": ["stubborn", "uncooperative", "resistant", "defiant", "rebellious"]},
    {"word": "acquiesce", "synonyms": ["comply", "agree", "yield", "accept", "consent"]},
    {"word": "resplendent", "synonyms": ["brilliant", "radiant", "dazzling", "gleaming", "magnificent"]},
    {"word": "effulgent", "synonyms": ["shining", "glowing", "luminous", "radiant", "brilliant"]},
    {"word": "magnanimous", "synonyms": ["generous", "charitable", "selfless", "benevolent", "forgiving"]}
  ]
}
